README.md
license.txt
setup.py
sacar_dinheiro_no_banco/__init__.py
sacar_dinheiro_no_banco/login.py
sacar_dinheiro_no_banco/status.py
sacar_dinheiro_no_banco.egg-info/PKG-INFO
sacar_dinheiro_no_banco.egg-info/SOURCES.txt
sacar_dinheiro_no_banco.egg-info/dependency_links.txt
sacar_dinheiro_no_banco.egg-info/top_level.txt