Metadata-Version: 2.1
Name: sacar_dinheiro_no_banco
Version: 1.0
Summary: Este pacote simula um login de uma pessoa que vai sacar dinheiro.
Author: João Paulo
Author-email: jpsampaiosampaio@gmail.com
Keywords: login,status,banco
License-File: license.txt
